cfautodoc/__init__.py
cfautodoc/autodoc.py
cfautodoc-0.1.data/scripts/cfautodoc
cfautodoc-0.1.dist-info/top_level.txt
cfautodoc-0.1.dist-info/METADATA
cfautodoc-0.1.dist-info/DESCRIPTION.rst
cfautodoc-0.1.dist-info/metadata.json
cfautodoc-0.1.dist-info/WHEEL
cfautodoc-0.1.dist-info/RECORD
