Metadata-Version: 2.0
Name: cfautodoc
Version: 0.1
Summary: Tool to document CloudFormation templates in Markdown.
Home-page: http://github.com/linuturk/cloudformation-autodoc
Author: Justin Phelps
Author-email: linuturk@onitato.com
License: MIT
Download-URL: http://github.com/linuturk/cloudformation-autodoc/tarball/master
Platform: UNKNOWN
Requires-Dist: argparse
